hu_bert2
