Metadata-Version: 2.1
Name: hu-bert2
Version: 0.0.2
Summary: PyPI first
Home-page: https://github.com/users/hzfei
Author: huzhen
Author-email: 1027551108@qq.com
License: UNKNOWN
Platform: UNKNOWN
Classifier: Programming Language :: Python :: 3
Classifier: License :: OSI Approved :: MIT License
Classifier: Operating System :: OS Independent
